{
  "date": "2026-05-21",
  "theme": "recursive realities",
  "links_direction": "strange loops, self-reference, recursive structures in nature",
  "motifs": [
    "Data",
    "Excel",
    "Nelle",
    "Dave",
    "\" prefix and the right files with an \"",
    "10 million",
    "Seti",
    "Radio",
    "Search",
    "Signals",
    "in 1960",
    "in 1959"
  ],
  "interesting_bits": [
    "\" prefix and the right files with an \"",
    "\" of data arrives better cleaning update external database High overhead of \"",
    "10 million",
    "\" serves as a benchmark for many of our SETI efforts. Two decades of analysis of the \"",
    "in 1960",
    "in 1959",
    "\") Session 3: A protocell (or protobiont) is (according to Wikipedia) \"",
    "since 2010"
  ],
  "links": [
    {
      "title": "Biological Computing User Stories | The Carpentries",
      "url": "https://carpentries.org/blog/2013/07/biological-computing-user-stories/",
      "concepts": [
        "Data",
        "Excel",
        "Nelle",
        "Dave"
      ],
      "reason": "fallback heuristic"
    },
    {
      "title": "Project Argus: A Global Search for our Cosmic Companions",
      "url": "https://www.setileague.org/articles/nids.htm",
      "concepts": [
        "Seti",
        "Radio",
        "Search",
        "Signals"
      ],
      "reason": "fallback heuristic"
    },
    {
      "title": "SOLU / Bioart Society | W 1 Day 6",
      "url": "https://bioartsociety.fi/projects/making-life/posts/w-1-day-6",
      "concepts": [
        "Session",
        "Workshop",
        "Some",
        "Work"
      ],
      "reason": "fallback heuristic"
    }
  ]
}